{
  "project_info": {
    "project_number": "852403813199",
    "project_id": "tokumemo-cd55e",
    "storage_bucket": "tokumemo-cd55e.appspot.com"
  },
  "client": [
    {
      "client_info": {
        "mobilesdk_app_id": "1:852403813199:android:7c72e4db5b4a00ef15633a",
        "android_client_info": {
          "package_name": "com.tokudai0000.tokumemo"
        }
      },
      "oauth_client": [
        {
          "client_id": "852403813199-fi2d53c3cuummno5o4urk4sgfo29481q.apps.googleusercontent.com",
          "client_type": 3
        }
      ],
      "api_key": [
        {
          "current_key": "AIzaSyBNrRQ-k1aknTyOvtKn4ZJbcsOjJknahlM"
        }
      ],
      "services": {
        "appinvite_service": {
          "other_platform_oauth_client": [
            {
              "client_id": "852403813199-fi2d53c3cuummno5o4urk4sgfo29481q.apps.googleusercontent.com",
              "client_type": 3
            },
            {
              "client_id": "852403813199-iu4qdcfe3grll8qv5l2t3nbdht5d655o.apps.googleusercontent.com",
              "client_type": 2,
              "ios_info": {
                "bundle_id": "com.akidon0000.univip",
                "app_store_id": "1582738889"
              }
            }
          ]
        }
      }
    }
  ],
  "configuration_version": "1"
}